Workbook

Sheet Read Me
B1: HENLEY HUB — FULL CODEBASE AUDIT REGISTER
B3: Rebuilt fresh 2026-07-23 (original workbook not found on Arnab's machine; rebuilt to the brief's spec, seeds re-derived from the repo's own handoff docs).
B4: Repo: github.com/henleynm-sketch/my-project · Branch audited: claude/henley-hub-platform-2wIAN (commit 71ae4de, 2026-07-06)
B6: METHOD
B7: Eleven read-only folder auditors (A1–A11) each read every file in their assigned folder (see Agent Roster). One orchestrator (A0) de-duplicated, re-graded severity against the Rubric, and ran a cross-cutting sweep for issues no single folder owns. No agent edited, committed, or ran any write command. This brief writes no code.
B9: EVIDENCE GATE
B10: No row exists without a real repo-relative file path and a line number or symbol an agent actually read. Context-known rows (Source = Context-known) were seeded from handoff docs, NOT from reading code; each started at Status = Verify and was Confirmed or Rejected by the owning agent pointing at the actual code. Rejected rows keep their row and record why. Secret VALUES never appear anywhere in this workbook — file and variable names only.
B12: LIMITATIONS
B13: Static read-only review: nothing was executed, so runtime-only behaviour (race conditions, third-party API responses, prod config) is inferred from code. Docs vs repo drift is resolved in favour of the repo. The QuickBooks guardrail files were read and reported on but no fix may edit them directly. Door 1 and v1 API scopes are frozen contracts — findings recorded, changes not proposed.
B15: HOW TO READ
B16: Sort Issue Register by Priority (col N, descending). Priority = severity weight × likelihood ÷ effort — quick wins rank above slow ones at equal severity. Check Summary readiness: 'Rows with no file path yet' must be 0 before trusting this register. Fix phase: when a row is fixed, set Status = Fixed and paste the commit hash in col T.

Sheet Rubric
A1: SEVERITY
A2: S1 | B2: 8 | C2: Critical: a client/sub can reach another project's data or financials; role gating bypassable; exposed/committed secrets; destructive data-loss path reachable in prod.
A3: S2 | B3: 4 | C3: Security/reliability hardening: missing server-side validation on a mutation, missing authz on a route, non-durable rate limit/idempotency, unhandled integration failure that corrupts state, no backups.
A4: S3 | B4: 2 | C4: Correctness/performance: N+1s, unbounded queries, float money at an edge, contained wrong logic, missing indexes/cascades.
A5: S4 | B5: 1 | C5: UI polish, hardcoded hex vs tokens, dead code, docs drift, tidy-up.
A7: LIKELIHOOD
A8: High | B8: 3 | C8: Bites in normal production use — on the default path or triggered by any curious user.
A9: Medium | B9: 2 | C9: Needs a specific-but-plausible situation (role combination, integration hiccup, scale).
A10: Low | B10: 1 | C10: Edge case, future migration, or requires deliberate unusual action.
A12: EFFORT
A13: S | B13: 1 | C13: Under an hour, one writer, one file or a small set.
A14: M | B14: 2 | C14: Roughly a half-day; touches several files or needs a small migration.
A15: L | B15: 3 | C15: Multi-day; schema change, storage move, or architectural rework.
A17: PRIORITY | C17: Formula in Issue Register col N: severity weight × likelihood weight ÷ effort weight. Quick wins outrank slow ones at equal severity. Ask A0 to switch to pure risk (ignore effort) if preferred.
A19: CATEGORY | C19: Data Isolation · Security · Secrets · Validation · Reliability · Correctness · Performance · Config/Deploy · UI/UX · Code Quality
A21: STATUS
A22: Verify | C22: Seeded from context/handoff notes; not yet checked against the repo. None may remain at audit acceptance.
A23: Confirmed | C23: An agent pointed at the actual file and line.
A24: Rejected | C24: Checked against the repo and found not to hold; the row stays, with the reason, for the record.
A25: Fixed | C25: Fix landed — requires a commit hash in col T, tsc --noEmit clean, and a hard-refresh render.

Sheet Agent Roster
A1: Agent | B1: Folder / scope | C1: Headline hunt | D1: Seeded rows owned
A2: A0 | B2: Orchestrator | C2: Assign, merge, de-duplicate, normalise severity, cross-cutting sweep, final review | D2: —
A3: A1 | B3: packages/db (prisma schema + seeds) | C3: Indexes, cascades, unvalidated status strings, seed safety | D3: HH-012
A4: A2 | B4: apps/web/src/lib core (roles, actions, notifications, assistant) | C4: Bypassable permission helpers, float money, duplicate clients | D4: —
A5: A3 | B5: apps/web/src/lib/services | C5: Queries missing a project scope, N+1s, unbounded finds | D5: HH-002
A6: A4 | B6: apps/web/src/lib/api | C6: Rate limit + idempotency durability, missing scope checks | D6: HH-014
A7: A5 | B7: apps/web/src/app/api (v1, oauth, external) | C7: Scope/action mismatches, unvalidated bodies, Door 1 integrity | D7: HH-013
A8: A6 | B8: app/(app): projects, jobs, schedule, files, selections, tasks | C8: Sub-tab queries not scoped to the current job; tester's files/selections findings | D8: HH-001, HH-003
A9: A7 | B9: app/(app): crm, clients, estimates, financials, inbox, vendors, contracts, dashboard | C9: Missing server-side validation, role leakage | D9: HH-004, HH-015
A10: A8 | B10: app/(app)/settings + auth.ts / auth.config.ts / middleware.ts + login/invite/reset routes | C10: In-component action helpers, middleware matcher gaps, demo passwords | D10: HH-010
A11: A9 | B11: components + globals.css + layout + tailwind config | C11: Hardcoded hex, comma trap, dark-mode tokens, tap targets | D11: HH-017, HH-018
A12: A10 | B12: lib integration clients (quickbooks, jobtread, quo, m365, sharepoint, oauth) + app integrations pages | C12: Unhandled failures, secrets read from source, missing retries | D12: HH-005, HH-007, HH-008, HH-016
A13: A11 | B13: Root config, .github, deploy, docs, ecosystem.config.js, imports | C13: CI, backups, PM2/SQLite, destructive resets, B1 scaffold noise | D13: HH-006, HH-009, HH-011

Sheet Issue Register
A1: ID | B1: Agent | C1: Source | D1: Status | E1: Folder | F1: File path(s) | G1: Line / symbol | H1: Category | I1: Title | J1: What is wrong | K1: Why it matters | L1: Severity | M1: Likelihood | N1: Priority | O1: Effort | P1: Proposed fix | Q1: Fix touches | R1: How to verify fix | S1: Guardrail | T1: Commit hash (fix)
A2: HH-001 | B2: A6 | C2: Context-known | D2: Confirmed | E2: projects/files | F2: apps/web/src/lib/services/fileService.ts | G2: 127 (storeFileBinary local fallback) | H2: Reliability | I2: Files: cloud storage backend not wired — binaries on local disk | J2: Uploads are written to local disk (public/uploads/documents) via fs writeFile; Document.url points at a local path. [AUDIT VERDICT] Local-disk fallback writes documents/log photos under public/ served as authz-free static URLs (A3-1, A6-4); the role-gated proxy at api/files/[id]/route.ts:24-43 exists but every UI links direct public URLs and the proxy redirects to them, nullifying it (A0-2); v1 upload also has no size cap (A5-7). | K2: Not production-portable; files lost on redeploy/migration; no access control on the public path. | L2: S2 | M2: High | N2: =IF(OR($L2="",$M2="",$O2=""),"",IF($L2="S1",8,IF($L2="S2",4,IF($L2="S3",2,1)))*IF($M2="High",3,IF($M2="Medium",2,1))/IF($O2="S",1,IF($O2="M",2,3))) -> 6 | O2: M | P2: Move binary storage to SharePoint/R2/S3 behind a storage interface; keep Document.url abstract. | Q2: apps/web/src/app/(app)/files/*, src/lib/storage.ts | R2: Upload a file, redeploy, confirm it still serves; confirm URL not publicly guessable.
A3: HH-002 | B3: A3 | C3: Context-known | D3: Confirmed | E3: lib/services | F3: apps/web/src/lib/services/fileService.ts | G3: 70 (createStoredFile), 147 (deleteFile) | H3: Security | I3: fileService has no auth/role/assignment checks; v1 path creates pending stub rows | J3: Service validates input but never checks role or ProjectAssignment; createFileMetadata writes url="", pending=true rows with no binary. [AUDIT VERDICT] fileService has no internal auth (call sites gate it) and carries stub/dead rows: createStoredFile is dead code with zero validation (A3-11); deleteFile removes only the DB row, leaving the binary orphaned and still downloadable (A3-2). | K3: Any caller reusing the service skips gating; stub rows accumulate. | L3: S2 | M3: Medium | N3: =IF(OR($L3="",$M3="",$O3=""),"",IF($L3="S1",8,IF($L3="S2",4,IF($L3="S3",2,1)))*IF($M3="High",3,IF($M3="Medium",2,1))/IF($O3="S",1,IF($O3="M",2,3))) -> 4 | O3: M | P3: Make the service self-guarding (session + assignment check) or document and enforce the trusted-caller boundary; clean pending rows. | Q3: apps/web/src/lib/services/fileService.ts | R3: Call service from a route without prior checks; expect deny.
A4: HH-003 | B4: A6 | C4: Context-known | D4: Confirmed | E4: projects/selections | F4: apps/web/src/app/(app)/selections/page.tsx | G4: 1-16 (ComingSoon stub) | H4: Code Quality | I4: Selections: entire feature is a stub (no write path, no service, no dueDate) | J4: Page is a ComingSoon placeholder; Selection model fields (status/decidedAt/notes) unused; no selectionService, no server actions; schema lacks dueDate. [AUDIT VERDICT] Selections is still a 16-line ComingSoon stub; Selection model (schema.prisma:171-181) lacks dueDate/clientVisible/createdAt and no selectionService exists (A6 seed_verdict). | K4: Roadmap feature blocked; dormant SELECTION_* notification events can never fire. | L4: S4 | M4: Low | N4: =IF(OR($L4="",$M4="",$O4=""),"",IF($L4="S1",8,IF($L4="S2",4,IF($L4="S3",2,1)))*IF($M4="High",3,IF($M4="Medium",2,1))/IF($O4="S",1,IF($O4="M",2,3))) -> 0.33333333 | O4: L | P4: Build per Master spec: schema dueDate, selectionService, actions, client-visible flow, budget roll-up. | Q4: packages/db/prisma/schema.prisma, new selectionService.ts, app/(app)/selections/* | R4: Feature walk as Client + Office roles.
A5: HH-004 | B5: A7 | C5: Context-known | D5: Confirmed | E5: contracts | F5: apps/web/src/app/(app)/contracts/page.tsx | G5: 94-127 (convertEstimate, depositPct) | H5: Correctness | I5: Contracts: manual record only — no e-sign, deposit never collected, logic lives in page actions | J5: No e-signature integration; qbInvoiceId never written (deposit recorded, not collected); no contractService — all logic in the two pages' "use server" actions. [AUDIT VERDICT] Contracts remain page-embedded actions with no e-sign/deposit-collection lifecycle; convertEstimate accepts an unbounded depositPct so negative or >100% deposits are possible (A7-8). | K5: Legal/cash-flow gap; page-embedded actions dodge the service layer and are hard to gate consistently. | L5: S2 | M5: Medium | N5: =IF(OR($L5="",$M5="",$O5=""),"",IF($L5="S1",8,IF($L5="S2",4,IF($L5="S3",2,1)))*IF($M5="High",3,IF($M5="Medium",2,1))/IF($O5="S",1,IF($O5="M",2,3))) -> 2.6666667 | O5: L | P5: Extract contractService; wire deposit invoice (QBO — guardrail); e-sign later per decision gate. | Q5: new contractService.ts, contracts pages | R5: Contract flow end-to-end with deposit path stubbed. | S5: QuickBooks guardrail
A6: HH-005 | B6: A10 | C6: Context-known | D6: Confirmed | E6: integrations/quickbooks | F6: HENLEY_HUB_CONTEXT.md | G6: 125-134 (Secrets pending rotation) | H6: Secrets | I6: QBO client ID + secret exposed in earlier chat logs — rotation pending | J6: Handoff doc says both were exposed in chat logs and still await rotation. [AUDIT VERDICT] QBO client id + client secret documented as leaked and pending rotation, still unrotated (A11-6, A11 seed_verdict). Runtime reads them from env, not source (A10 seed_verdict), but the committed doc records the exposure. | K6: Anyone with the transcript can impersonate the app to QBO. | L6: S1 | M6: Medium | N6: =IF(OR($L6="",$M6="",$O6=""),"",IF($L6="S1",8,IF($L6="S2",4,IF($L6="S3",2,1)))*IF($M6="High",3,IF($M6="Medium",2,1))/IF($O6="S",1,IF($O6="M",2,3))) -> 16 | O6: S | P6: Rotate in Intuit developer portal; update env on server; never store in repo/docs. | Q6: (env only) | R6: Old credentials rejected by Intuit after rotation. | S6: QuickBooks guardrail
A7: HH-006 | B7: A11 | C7: Context-known | D7: Confirmed | E7: root/git | F7: HENLEY_HUB_CONTEXT.md | G7: 125-134 (GitHub PAT in remote URL) | H7: Secrets | I7: GitHub PAT embedded in the git remote URL — rotation pending | J7: Remote URL on the dev machine embeds a PAT per handoff doc. [AUDIT VERDICT] GitHub PAT embedded in the git remote URL, documented as pending rotation and still unrotated (A11-6, A11 seed_verdict). | K7: PAT grants repo write to anyone who sees the remote config or logs. | L7: S1 | M7: Medium | N7: =IF(OR($L7="",$M7="",$O7=""),"",IF($L7="S1",8,IF($L7="S2",4,IF($L7="S3",2,1)))*IF($M7="High",3,IF($M7="Medium",2,1))/IF($O7="S",1,IF($O7="M",2,3))) -> 16 | O7: S | P7: Revoke PAT; switch to gh auth or a fresh fine-scoped PAT stored in the credential manager. | Q7: (dev machine git config) | R7: git remote -v shows no token; old PAT revoked on GitHub.
A8: HH-007 | B8: A10 | C8: Context-known | D8: Confirmed | E8: integrations/quo | F8: HENLEY_HUB_CONTEXT.md | G8: 130 (Quo API key) | H8: Secrets | I8: Quo API key pasted into chat — rotation pending | J8: Key was pasted into a chat transcript; new key should live only in QuoConfig.apiKey. [AUDIT VERDICT] Quo API key leaked and pending rotation; the doc commits its first 6 characters (A11-6, A11 seed_verdict). | K8: Client-texting API usable by anyone with the transcript. | L8: S1 | M8: Medium | N8: =IF(OR($L8="",$M8="",$O8=""),"",IF($L8="S1",8,IF($L8="S2",4,IF($L8="S3",2,1)))*IF($M8="High",3,IF($M8="Medium",2,1))/IF($O8="S",1,IF($O8="M",2,3))) -> 16 | O8: S | P8: Rotate in Quo; store only in QuoConfig; purge from any doc. | Q8: (Quo dashboard + Setting row) | R8: Old key returns 401.
A9: HH-008 | B9: A10 | C9: Context-known | D9: Confirmed | E9: assistant | F9: docs/status/BUILD-STATUS-3.md | G9: 72-73, 112 (Gemini key in transcript) | H9: Secrets | I9: Gemini API key leaked into chat transcript — rotation advised, may still be pending | J9: BUILD-STATUS-3 flags Nick's Gemini key as passed through chat. [AUDIT VERDICT] Nick's Gemini API key leaked into a committed chat transcript, unrotated (A11-6, A11 seed_verdict). Distinct from the runtime design flaw of passing the key as a URL query param (A2-13, kept as its own row). | K9: Billable API usable by transcript holders. | L9: S1 | M9: Medium | N9: =IF(OR($L9="",$M9="",$O9=""),"",IF($L9="S1",8,IF($L9="S2",4,IF($L9="S3",2,1)))*IF($M9="High",3,IF($M9="Medium",2,1))/IF($O9="S",1,IF($O9="M",2,3))) -> 16 | O9: S | P9: Rotate in Google AI Studio; update Setting/env. | Q9: (env only) | R9: Old key rejected.
A10: HH-009 | B10: A11 | C10: Context-known | D10: Confirmed | E10: deploy/db | F10: deploy/README.md | G10: 106-135 (setup; no backup step) | H10: Reliability | I10: No database backup mechanism for the shared live Postgres | J10: Nick + Arnab share one live Neon DB; only rollback artifact is a dated dev.db SQLite copy. No automated backup/rotation exists. [AUDIT VERDICT] No pg_dump/cron/snapshot anywhere in deploy docs, workflows, or scripts; live Neon DB holds 451 real clients with no backup mechanism (A11-1, A11 seed_verdict). | K10: One bad migration or destructive script loses live business data. | L10: S2 | M10: Medium | N10: =IF(OR($L10="",$M10="",$O10=""),"",IF($L10="S1",8,IF($L10="S2",4,IF($L10="S3",2,1)))*IF($M10="High",3,IF($M10="Medium",2,1))/IF($O10="S",1,IF($O10="M",2,3))) -> 8 | O10: S | P10: Enable Neon PITR/branch snapshots + nightly pg_dump to offsite storage; document restore drill. | Q10: deploy docs, cron | R10: Run a restore drill onto a scratch branch.
A11: HH-010 | B11: A8 | C11: Context-known | D11: Confirmed | E11: auth | F11: packages/db/prisma/seed.ts | G11: 31 (hashes 'demo') | H11: Security | I11: Every demo user shares password 'demo' | J11: All seeded users (CEO through Client roles) authenticate with the literal password 'demo'; prod-build smoke check for absent demo hints was deferred. [AUDIT VERDICT] seed.ts hashes literal 'demo' for every seeded login; README:39-51 documents all accounts; those 9 User rows plus real-client portal logins were migrated into live Postgres (A1-2, A11-5). See also the inline invite form that still mints 'demo' accounts (kept as a separate live-code row). | K11: If seeds ever run against prod (shared DB!), every role is open with a one-word password. | L11: S1 | M11: Medium | N11: =IF(OR($L11="",$M11="",$O11=""),"",IF($L11="S1",8,IF($L11="S2",4,IF($L11="S3",2,1)))*IF($M11="High",3,IF($M11="Medium",2,1))/IF($O11="S",1,IF($O11="M",2,3))) -> 16 | O11: S | P11: Gate demo credentials to dev; force strong passwords/invite flow in prod; verify seed guard. | Q11: packages/db/prisma/seed.ts, auth flow | R11: Login with 'demo' fails on prod build.
A12: HH-011 | B12: A11 | C12: Context-known | D12: Confirmed | E12: root/.github | F12: .github/workflows/ci.yml | G12: 42-48 (wrong cwd / DATABASE_URL) | H12: Config/Deploy | I12: CI never wired — verification is manual only | J12: Handoff doc lists CI as a to-do (prisma generate + tsc + build on push); repo now contains ci.yml/deploy.yml — confirm whether they actually run. [AUDIT VERDICT] CI never landed (PAT lacked workflow scope per deploy/README:149-158) and cannot pass as written: prisma generate / tsc run at repo root which has no schema or tsconfig (A11-2, A11 seed_verdict). | K12: Regressions land unnoticed; 'tsc clean' relies on humans remembering. | L12: S2 | M12: High | N12: =IF(OR($L12="",$M12="",$O12=""),"",IF($L12="S1",8,IF($L12="S2",4,IF($L12="S3",2,1)))*IF($M12="High",3,IF($M12="Medium",2,1))/IF($O12="S",1,IF($O12="M",2,3))) -> 12 | O12: S | P12: Ensure ci.yml runs on push to the working branch; require green before merge. | Q12: ​.github/workflows/ci.yml | R12: Push a commit; watch the Actions run.
A13: HH-012 | B13: A1 | C13: Context-known | D13: Confirmed | E13: packages/db | F13: packages/db/package.json | G13: 14 (db:reset) | H13: Reliability | I13: Destructive db:reset (prisma db push --force-reset) reachable against shared live DB | J13: db:reset wipes and reseeds; docs warn it destroys the QBO connection and live data; a seed guard (SEED_FORCE=1) is claimed — verify it actually blocks Postgres. [AUDIT VERDICT] db:reset = `prisma db push --force-reset && db:seed` force-wipes the shared live Neon DB before the seed guard can run (A1-0, A11-0); RUN_LOCAL.md:30 also trains Nick to 'answer y to any drop warning' now targeting the live DB (A11-10). | K13: One habitual command from either dev nukes the shared database. | L13: S1 | M13: Medium | N13: =IF(OR($L13="",$M13="",$O13=""),"",IF($L13="S1",8,IF($L13="S2",4,IF($L13="S3",2,1)))*IF($M13="High",3,IF($M13="Medium",2,1))/IF($O13="S",1,IF($O13="M",2,3))) -> 16 | O13: S | P13: Verify/strengthen seed guard: hard-fail on non-SQLite URL unless SEED_FORCE=1; remove script from prod path. | Q13: packages/db/package.json, seed.ts | R13: Run db:reset against a Postgres URL; expect refusal.
A14: HH-013 | B14: A5 | C14: Context-known | D14: Rejected | E14: app/api/v1 | F14: apps/web/src/lib/services/timeEntryService.ts | G14: 94 (approveTimeEntry) | H14: Correctness | I14: v1 approve sets qbReady but never calls pushTimeActivity | J14: Documented known gap: API-approved time entries are marked ready yet never pushed to QBO; OpenAPI caveat never added. [AUDIT VERDICT] No longer true: approveTimeEntry now calls pushTimeActivityToQBO and the v1 approve route delegates to it. The live residual risk is the read-then-write idempotency race (double-post), tracked as its own row (A10-0), not a missing push. | K14: Approved time silently never reaches payroll/accounting. | L14: S3 | M14: High | N14: =IF(OR($L14="",$M14="",$O14=""),"",IF($L14="S1",8,IF($L14="S2",4,IF($L14="S3",2,1)))*IF($M14="High",3,IF($M14="Medium",2,1))/IF($O14="S",1,IF($O14="M",2,3))) -> 6 | O14: S | P14: Either call the push (guardrail — via existing helper, no edits to it) or document the manual push step in OpenAPI. | Q14: approve route, openapi.json | R14: Approve via API; confirm TimeActivity appears or caveat documented. | S14: QuickBooks guardrail
A15: HH-014 | B15: A4 | C15: Context-known | D15: Confirmed | E15: lib/api | F15: apps/web/src/lib/api/rateLimit.ts | G15: 12-13 (Maps); idempotency.ts:12-13 | H15: Reliability | I15: Rate limiter and idempotency cache are in-memory only | J15: Token bucket and idempotency response cache live in process memory; both reset on restart and shatter under multi-instance deploy. [AUDIT VERDICT] Rate limit and idempotency both hold state in module-level Maps with TODO comments; restarts reset budgets and drop the replay cache, and there is no cross-instance store — password-reset/login throttling is keyed only by attacker-controlled email (A4-0, A4-1, A4-5, A5-1, A8-3, A2-2). Cache also grows unbounded (lazy eviction). | K15: Replay protection and abuse limits silently vanish in prod topology. | L15: S2 | M15: Medium | N15: =IF(OR($L15="",$M15="",$O15=""),"",IF($L15="S1",8,IF($L15="S2",4,IF($L15="S3",2,1)))*IF($M15="High",3,IF($M15="Medium",2,1))/IF($O15="S",1,IF($O15="M",2,3))) -> 4 | O15: M | P15: Back both with the DB (or Redis when hosting lands); keep interface unchanged (frozen contract). | Q15: rateLimit.ts, idempotency.ts | R15: Restart server mid-window; limits persist.
A16: HH-015 | B16: A7 | C16: Context-known | D16: Rejected | E16: vendors | F16: apps/web/src/app/(app)/vendors/page.tsx | G16: 19-46 (findMany + compliance counts) | H16: Correctness | I16: Vendors page crash reported by Arnab — still open, unreproduced | J16: Reported page error; page and tsc statically clean; no console output ever supplied. [AUDIT VERDICT] Could not confirm: page + vendorActions read in full, no crash path found; coiExpiresAt is null-guarded; tsc statically clean. Rejected for lack of evidence — reopen with console/terminal output if it recurs. | K16: A core directory page may be broken for real users. | L16: S3 | M16: Medium | N16: =IF(OR($L16="",$M16="",$O16=""),"",IF($L16="S1",8,IF($L16="S2",4,IF($L16="S3",2,1)))*IF($M16="High",3,IF($M16="Medium",2,1))/IF($O16="S",1,IF($O16="M",2,3))) -> 4 | O16: S | P16: Reproduce with seeded data volume; fix root cause or close with evidence. | Q16: vendors page files | R16: Load /vendors as each role with full data.
A17: HH-016 | B17: A10 | C17: Context-known | D17: Confirmed | E17: integrations/jobtread | F17: apps/web/src/lib/jobtread.ts | G17: 108 (jtQuery), 147 (page-size) | H17: Reliability | I17: JobTread sync: 413 page-size ceilings; pre-fix runs may have failed silently | J17: Pave API rejects large pages (25/50 item ceilings); runs before commit 02823c0 could silently miss customers; second-run zero-diff never verified. [AUDIT VERDICT] jtQuery is single-shot with no retry/backoff and relies on page-size tuning to avoid Pave 413; a mid-run fetch failure aborts the sync while keeping partial writes (jobtreadSync.ts:706-710), so sync fails silently (A10 seed_verdict; broader no-retry across all integrations kept as row A10-13). | K17: Sync believed complete may be missing records (~369 customers expected). | L17: S2 | M17: Medium | N17: =IF(OR($L17="",$M17="",$O17=""),"",IF($L17="S1",8,IF($L17="S2",4,IF($L17="S3",2,1)))*IF($M17="High",3,IF($M17="Medium",2,1))/IF($O17="S",1,IF($O17="M",2,3))) -> 4 | O17: M | P17: Verify pagination on every query; run sync twice; diff counts vs JobTread. | Q17: jobtread.ts, jobtreadSync.ts | R17: Second run reports zero new rows; counts match.
A18: HH-017 | B18: A9 | C18: Context-known | D18: Confirmed | E18: components | F18: apps/web/src/components/M365Card.tsx | G18: 177 (also QuoCard:197, HenleyTasksCard:151, ApiKeysManager:232/295) | H18: UI/UX | I18: .hh-panel backdrop-filter traps position:fixed descendants (latent in 3 cards) | J18: backdrop-filter creates a containing block; fixed-position children inside these cards anchor to the panel, not the viewport. Known, deliberately unfixed. [AUDIT VERDICT] Non-portaled fixed-position modals are trapped inside the backdrop-filtered .hh-panel; a backdrop-filter ancestor makes fixed children position relative to the panel, not the viewport (A9-0). | K18: Dropdowns/modals inside the cards render clipped or misplaced. | L18: S3 | M18: Medium | N18: =IF(OR($L18="",$M18="",$O18=""),"",IF($L18="S1",8,IF($L18="S2",4,IF($L18="S3",2,1)))*IF($M18="High",3,IF($M18="Medium",2,1))/IF($O18="S",1,IF($O18="M",2,3))) -> 4 | O18: S | P18: Portal the fixed elements or drop backdrop-filter on affected ancestors (token-safe). | Q18: three card components | R18: Open each card's overlay on a scrolled page.
A19: HH-018 | B19: A9 | C19: Context-known | D19: Rejected | E19: styling | F19: apps/web/src/app/globals.css | G19: 690-1373 (selector lists audited) | H19: UI/UX | I19: Comma trap: unescaped commas in Tailwind arbitrary values break the whole PostCSS build | J19: Documented past pain: one bad arbitrary value kills styling app-wide, silently. [AUDIT VERDICT] Audited every selector list; all selectors are valid CSS and no rule is killed by a bad member — the Tailwind/CSS comma trap is not present (A9 seed_verdict). | K19: A single class typo takes down the entire UI's styles. | L19: S4 | M19: Low | N19: =IF(OR($L19="",$M19="",$O19=""),"",IF($L19="S1",8,IF($L19="S2",4,IF($L19="S3",2,1)))*IF($M19="High",3,IF($M19="Medium",2,1))/IF($O19="S",1,IF($O19="M",2,3))) -> 1 | O19: S | P19: Grep for risky arbitrary values; add a lint rule or stylelint check to CI. | Q19: globals.css, CI config | R19: Introduce a test violation locally; lint catches it.
A20: HH-019 | B20: A7 | C20: Agent-found | D20: Confirmed | E20: crm+money pages | F20: apps/web/src/app/(app)/crm/[id]/page.tsx; apps/web/src/app/(app)/clients/[id]/page.tsx; apps/web/src/app/(app)/estimates/[id]/page.tsx; apps/web/src/app/(app)/crm/page.tsx; apps/web/src/app/(app)/estimates/new/page.tsx; apps/web/src/app/(app)/schedule/page.tsx | G20: crm/[id]:131 · clients/[id]:160/198 · estimates/[id]:14 · crm/page:18 · estimates/new:30 · schedule/page:19-45 | H20: Data Isolation | I20: Detail/list pages render financials & cross-client PII with no read gate | J20: The CRM deal detail, client record, estimate detail, sales pipeline board, new-estimate, and /schedule pages all fetch and render other projects' contract values, estimate totals, and client PII without any canViewAllProjects/role gate. Middleware only enforces login, so any authenticated CLIENT/SUB/FIELD user who types the URL reads financials and every customer's data. List pages gate; their sibling detail pages do not. [regraded A6-1 S2->S1 (folded into S1 cross-project read leak)] [Also reported by: A6 — 6 findings merged] | K20: Clients must never see financials or other clients' data; this is the Master's core promise and the only defense (page-level gating) is absent on these surfaces. | L20: S1 | M20: High | N20: =IF(OR($L20="",$M20="",$O20=""),"",IF($L20="S1",8,IF($L20="S2",4,IF($L20="S3",2,1)))*IF($M20="High",3,IF($M20="Medium",2,1))/IF($O20="S",1,IF($O20="M",2,3))) -> 12 | O20: M | P20: Add the same auth()+canViewAllProjects(role) gate the list pages use at the top of each page (return notFound()/denial for other roles); for CLIENT scope queries to their own clientId. | Q20: apps/web/src/app/(app)/crm/[id]/page.tsx; apps/web/src/app/(app)/clients/[id]/page.tsx; apps/web/src/app/(app)/estimates/[id]/page.tsx; apps/web/src/app/(app)/crm/page.tsx; apps/web/src/app/(app)/estimates/new/page.tsx; apps/web/src/app/(app)/schedule/page.tsx | R20: As a CLIENT/SUB/FIELD demo user request /crm/<id>, /clients/<id>, /estimates/<id>, /crm, /schedule — expect denial or own-data only.
A21: HH-020 | B21: A7 | C21: Agent-found | D21: Confirmed | E21: crm+money pages | F21: apps/web/src/app/(app)/inbox/page.tsx | G21: inbox/page.tsx:118-129 (activeThread findUnique) | H21: Data Isolation | I21: Inbox thread IDOR — active thread fetch bypasses the role-scoped where clause | J21: The thread list is scoped by buildWhere(), but the active conversation loads via prisma.thread.findUnique({where:{id:activeId}}) using the client-supplied ?threadId directly. A CLIENT/SUB can pass any thread id and read another client's full email/SMS history. | K21: Role scoping exists but is skipped for exactly the query that returns full message bodies; a client-supplied id is trusted without ownership check. | L21: S1 | M21: High | N21: =IF(OR($L21="",$M21="",$O21=""),"",IF($L21="S1",8,IF($L21="S2",4,IF($L21="S3",2,1)))*IF($M21="High",3,IF($M21="Medium",2,1))/IF($O21="S",1,IF($O21="M",2,3))) -> 24 | O21: S | P21: Fetch the active thread with findFirst applying the same buildWhere role constraints, returning null on no match. | Q21: apps/web/src/app/(app)/inbox/page.tsx | R21: As CLIENT A request /inbox?threadId=<B's thread>; pane must show empty state, not B's messages.
A22: HH-021 | B22: A6 | C22: Agent-found | D22: Confirmed | E22: projects+jobs | F22: apps/web/src/app/(app)/projects/new/page.tsx; apps/web/src/app/(app)/clients/new/page.tsx; apps/web/src/app/(app)/vendors/vendorActions.ts | G22: projects/new/page.tsx:15-58 · clients/new/page.tsx:6-22 · vendors/vendorActions.ts:103/125 | H22: Data Isolation | I22: Server actions/pages mutate and leak data with no auth() check | J22: The New Job page never calls auth() — it renders the full client list to any role and its inline create action writes prisma.project.create with arbitrary clientId/contract cents. The new-lead create action and the vendor listExpiringCoi/listMissingW9 'use server' exports likewise perform no session/role check, so any authenticated user (or crafted Next-Action POST) can create records or read vendor compliance data. [regraded A7-6/A7-7 S2->S1 (folded; New-Job client-list leak drives S1)] [Also reported by: A7 — 3 findings merged] | K22: Every other mutation checks session+role; these check neither. New Job additionally leaks every client's name to CLIENT (cross-client read), and dead-but-live 'use server' exports get invokable action IDs. | L22: S1 | M22: Medium | N22: =IF(OR($L22="",$M22="",$O22=""),"",IF($L22="S1",8,IF($L22="S2",4,IF($L22="S3",2,1)))*IF($M22="High",3,IF($M22="Medium",2,1))/IF($O22="S",1,IF($O22="M",2,3))) -> 8 | O22: M | P22: Add auth()+canViewAllProjects(role) at the top of each page render and re-check inside every create action before any query; delete the unused vendor list actions or gate them with the same isManager check as the CRUD actions above them. | Q22: apps/web/src/app/(app)/projects/new/page.tsx; apps/web/src/app/(app)/clients/new/page.tsx; apps/web/src/app/(app)/vendors/vendorActions.ts | R22: As CLIENT open /projects/new and /clients/new — expect redirect and no row created; confirm vendor actions reject non-managers.
A23: HH-022 | B23: A0 | C23: Agent-found | D23: Confirmed | E23: cross-cutting | F23: apps/web/src/app/(app)/projects/[id]/changeOrderActions.ts; apps/web/src/app/(app)/projects/[id]/timeActions.ts; apps/web/src/app/(app)/inbox/inboxActions.ts; apps/web/src/app/(app)/projects/[id]/page.tsx | G23: changeOrderActions.ts:25-66 · projects/[id]/timeActions.ts:10-42 · inbox/inboxActions.ts:16-23 · projects/[id]/page.tsx:222-232 | H23: Data Isolation | I23: Field/Sub-reachable mutations skip ProjectAssignment; the one correct pattern was never extracted | J23: changeOrderActions holds the app's only complete server-action authz pattern (role → ProjectAssignment fallback → CLIENT ownership+clientVisible). ProjectAssignment is consulted in only three files app-wide. Every other Field/Sub-reachable mutation skips it: clockInAction accepts any projectId, replyToThread lets FIELD reply to any thread, updateMilestone trusts a form-supplied milestone id with no project scoping — so a worker can act on projects they aren't assigned to. [regraded A0-5 S3->S2, A7-10 S3->S2 (unified as missing-authz-on-mutation)] [Also reported by: A6, A7 — 4 findings merged] | K23: Fixing holes one-off leaves the next action to repeat the mistake; correct code exists and only needs hoisting to a shared requireProjectAccess helper. | L23: S2 | M23: Medium | N23: =IF(OR($L23="",$M23="",$O23=""),"",IF($L23="S1",8,IF($L23="S2",4,IF($L23="S3",2,1)))*IF($M23="High",3,IF($M23="Medium",2,1))/IF($O23="S",1,IF($O23="M",2,3))) -> 4 | O23: M | P23: Extract internalForProject/deciderForChangeOrder into lib/access.ts as requireProjectAccess(user, projectId); call it from clockInAction, replyToThread (resolve thread→project first), and updateMilestone. | Q23: apps/web/src/lib/roles.ts; apps/web/src/app/(app)/inbox/inboxActions.ts; apps/web/src/app/(app)/projects/[id]/page.tsx; apps/web/src/app/(app)/projects/[id]/changeOrderActions.ts; apps/web/src/app/(app)/projects/[id]/timeActions.ts | R23: As FIELD assigned to project A, invoke clockInAction/replyToThread/updateMilestone against project B → Not authorized, no row written.
A24: HH-023 | B24: A0 | C24: Agent-found | D24: Confirmed | E24: cross-cutting | F24: apps/web/src/lib/services/milestoneService.ts; apps/web/src/app/(app)/projects/[id]/page.tsx | G24: milestoneService.ts:43 · projects/[id]/page.tsx:127/375-398 | H24: Data Isolation | I24: Milestone clientVisible flag is non-functional end-to-end | J24: createMilestone defaults clientVisible to true (opposite of every sibling service), and the project detail page renders all project.milestones to CLIENT with no clientVisible filter (the client dashboard does filter). Internal-only milestones ('chase sub for deficiency', 'hold invoice') are exposed to the client. [regraded A3-8 S4->S2 (folded into the compound client-exposure)] [Also reported by: A3, A6 — 3 findings merged] | K24: The Master promises clients see only client-visible milestones; today the mark defaults on and the main surface ignores it. | L24: S2 | M24: High | N24: =IF(OR($L24="",$M24="",$O24=""),"",IF($L24="S1",8,IF($L24="S2",4,IF($L24="S3",2,1)))*IF($M24="High",3,IF($M24="Medium",2,1))/IF($O24="S",1,IF($O24="M",2,3))) -> 12 | O24: S | P24: Default clientVisible to input.clientVisible ?? false, and filter the detail-page render for CLIENT the same way dailyLogs already are. | Q24: apps/web/src/lib/services/milestoneService.ts; apps/web/src/app/(app)/projects/[id]/page.tsx | R24: Create a milestone without clientVisible → false in DB; as the project's client it is absent from dashboard and detail until toggled visible.
A25: HH-024 | B25: A8 | C25: Agent-found | D25: Confirmed | E25: settings+auth | F25: apps/web/src/app/(app)/settings/page.tsx | G25: settings/page.tsx:369-396/659-687/691 (inline inviteUser + dual forms) | H25: Security | I25: Inline invite form mints 'demo'-password production accounts beside the secure flow | J25: Settings→Team renders two invite UIs back to back: the top form calls an inline inviteUser that creates a live User (any role incl CEO/OFFICE) with bcrypt.hash('demo',10), prints the temporary password on screen, and requires no password change or verification. Directly below it, the hardened token-based InvitePanel (lib/actions/auth.ts) does it correctly. Nick will use whichever is on top. [Also reported by: A0 — 2 findings merged] | K25: 'demo' is publicly documented (README, sign-in hint, landing page); with auth.ts having no active/env gate, every account minted this way is takeover-able until the user manually changes the password. | L25: S1 | M25: High | N25: =IF(OR($L25="",$M25="",$O25=""),"",IF($L25="S1",8,IF($L25="S2",4,IF($L25="S3",2,1)))*IF($M25="High",3,IF($M25="Medium",2,1))/IF($O25="S",1,IF($O25="M",2,3))) -> 24 | O25: S | P25: Delete the inline inviteUser action and its form block; leave the token-based InvitePanel as the only invite path. | Q25: apps/web/src/app/(app)/settings/page.tsx; apps/web/src/components/settings/InvitePanel.tsx | R25: Settings#team shows exactly one invite form; inviting creates an Invite row with tokenHash and no User until acceptance; email+'demo' fails for new invitees.
A26: HH-025 | B26: A0 | C26: Agent-found | D26: Confirmed | E26: cross-cutting | F26: apps/web/src/app/page.tsx | G26: 5-11 (ROLES const) and 186-199 (details render) | H26: Security | I26: Public landing page advertises the five demo account emails whose shared password is 'demo' | J26: The unauthenticated landing page hardcodes and renders the five demo login emails (kyle@henleyhub.com, morgan@henleyhub.com, jess@henleyhub.com, tile-pro@subs.com, rachel.t@example.com) in a 'Role access — what each login sees' disclosure. A11 established these accounts exist in the real shared Neon DB with password 'demo' (README.md:39-51), and A8 established the invite flow keeps minting 'demo'-password accounts. No single folder agent saw the full chain: the landing page publishes the usernames, the README publishes the password, and the accounts are live — an unauthenticated visitor can log in as CEO in three clicks. The same email list is duplicated in apps/web/src/components/DemoRoleSwitcher.tsx:6-12 (that one is gated behind Settings). The page also runs unauthenticated prisma.project.count/prisma.user.count (lines 22-27), leaking org stats pre-login. | K26: Completes a working credential-stuffing recipe against the production CEO account. This is the missing link that upgrades A8/A11's 'demo password' findings from hygiene to an exploitable chain. | L26: S1 | M26: High | N26: =IF(OR($L26="",$M26="",$O26=""),"",IF($L26="S1",8,IF($L26="S2",4,IF($L26="S3",2,1)))*IF($M26="High",3,IF($M26="Medium",2,1))/IF($O26="S",1,IF($O26="M",2,3))) -> 24 | O26: S | P26: Delete the ROLES const and the role-access <details> block from app/page.tsx; remove or rotate the five demo accounts in the live DB (or set active=false once auth.ts honors it per A8); drop the unauthenticated prisma counts or replace with static copy. | Q26: apps/web/src/app/page.tsx | R26: Load / while signed out: no account emails and no live DB stats render; attempt login with kyle@henleyhub.com / demo fails.
... A101: HH-100 | B101: A7 | C101: Agent-found | D101: Confirmed | E101: crm+money pages | F101: apps/web/src/app/(app)/import/page.tsx | G101: importCsv row loop (lines 45-126) | H101: Reliability | I101: CSV import runs unbounded sequential queries with no transaction or size cap | J101: Each row issues up to 3 sequential awaited queries (findFirst client, create client, findFirst/create project) with no row limit, no batching, and no transaction. A large HubSpot export (thousands of rows) runs for minutes inside one server action and, if it times out or errors mid-file, leaves a partial import with no report of where it stopped. | K101: This is the designated one-shot cutover path for 451+ real customers; a mid-import failure against the shared Neon database is plausible and confusing (re-run is mostly idempotent via email/name match, but rows without email always create duplicates on retry). | L101: S3 | M101: Medium | N101: =IF(OR($L101="",$M101="",$O101=""),"",IF($L101="S1",8,IF($L101="S2",4,IF($L101="S3",2,1)))*IF($M101="High",3,IF($M101="Medium",2,1))/IF($O101="S",1,IF($O101="M",2,3))) -> 2 | O101: M | P101: Chunk rows (e.g. 50 per $transaction), pre-fetch existing clients by email in one query, and cap/validate file size; report the last processed row on failure. | Q101: apps/web/src/app/(app)/import/page.tsx | R101: Import a 1000-row CSV twice: first run completes in seconds; second run creates 0 duplicates including rows without email.
N102: =IF(OR($L102="",$M102="",$O102=""),"",IF($L102="S1",8,IF($L102="S2",4,IF($L102="S3",2,1)))*IF($M102="High",3,IF($M102="Medium",2,1))/IF($O102="S",1,IF($O102="M",2,3)))
N103: =IF(OR($L103="",$M103="",$O103=""),"",IF($L103="S1",8,IF($L103="S2",4,IF($L103="S3",2,1)))*IF($M103="High",3,IF($M103="Medium",2,1))/IF($O103="S",1,IF($O103="M",2,3)))
N104: =IF(OR($L104="",$M104="",$O104=""),"",IF($L104="S1",8,IF($L104="S2",4,IF($L104="S3",2,1)))*IF($M104="High",3,IF($M104="Medium",2,1))/IF($O104="S",1,IF($O104="M",2,3)))
N105: =IF(OR($L105="",$M105="",$O105=""),"",IF($L105="S1",8,IF($L105="S2",4,IF($L105="S3",2,1)))*IF($M105="High",3,IF($M105="Medium",2,1))/IF($O105="S",1,IF($O105="M",2,3)))
N106: =IF(OR($L106="",$M106="",$O106=""),"",IF($L106="S1",8,IF($L106="S2",4,IF($L106="S3",2,1)))*IF($M106="High",3,IF($M106="Medium",2,1))/IF($O106="S",1,IF($O106="M",2,3)))
N107: =IF(OR($L107="",$M107="",$O107=""),"",IF($L107="S1",8,IF($L107="S2",4,IF($L107="S3",2,1)))*IF($M107="High",3,IF($M107="Medium",2,1))/IF($O107="S",1,IF($O107="M",2,3)))
N108: =IF(OR($L108="",$M108="",$O108=""),"",IF($L108="S1",8,IF($L108="S2",4,IF($L108="S3",2,1)))*IF($M108="High",3,IF($M108="Medium",2,1))/IF($O108="S",1,IF($O108="M",2,3)))
N109: =IF(OR($L109="",$M109="",$O109=""),"",IF($L109="S1",8,IF($L109="S2",4,IF($L109="S3",2,1)))*IF($M109="High",3,IF($M109="Medium",2,1))/IF($O109="S",1,IF($O109="M",2,3)))
N110: =IF(OR($L110="",$M110="",$O110=""),"",IF($L110="S1",8,IF($L110="S2",4,IF($L110="S3",2,1)))*IF($M110="High",3,IF($M110="Medium",2,1))/IF($O110="S",1,IF($O110="M",2,3)))
N111: =IF(OR($L111="",$M111="",$O111=""),"",IF($L111="S1",8,IF($L111="S2",4,IF($L111="S3",2,1)))*IF($M111="High",3,IF($M111="Medium",2,1))/IF($O111="S",1,IF($O111="M",2,3)))
N112: =IF(OR($L112="",$M112="",$O112=""),"",IF($L112="S1",8,IF($L112="S2",4,IF($L112="S3",2,1)))*IF($M112="High",3,IF($M112="Medium",2,1))/IF($O112="S",1,IF($O112="M",2,3)))
N113: =IF(OR($L113="",$M113="",$O113=""),"",IF($L113="S1",8,IF($L113="S2",4,IF($L113="S3",2,1)))*IF($M113="High",3,IF($M113="Medium",2,1))/IF($O113="S",1,IF($O113="M",2,3)))
... N141: =IF(OR($L141="",$M141="",$O141=""),"",IF($L141="S1",8,IF($L141="S2",4,IF($L141="S3",2,1)))*IF($M141="High",3,IF($M141="Medium",2,1))/IF($O141="S",1,IF($O141="M",2,3)))

Sheet Folder Health
A1: Agent | B1: Folder | C1: S1 | D1: S2 | E1: S3 | F1: S4 | G1: Confirmed | H1: Rejected | I1: Open (Confirmed, unfixed) | J1: Health score
A2: A1 | B2: packages/db (prisma schema + seeds) | C2: =COUNTIFS('Issue Register'!$B:$B,$A2,'Issue Register'!$L:$L,"S1",'Issue Register'!$D:$D,"<>Rejected") -> 1 | D2: =COUNTIFS('Issue Register'!$B:$B,$A2,'Issue Register'!$L:$L,"S2",'Issue Register'!$D:$D,"<>Rejected") -> 1 | E2: =COUNTIFS('Issue Register'!$B:$B,$A2,'Issue Register'!$L:$L,"S3",'Issue Register'!$D:$D,"<>Rejected") -> 5 | F2: =COUNTIFS('Issue Register'!$B:$B,$A2,'Issue Register'!$L:$L,"S4",'Issue Register'!$D:$D,"<>Rejected") -> 0 | G2: =COUNTIFS('Issue Register'!$B:$B,$A2,'Issue Register'!$D:$D,"Confirmed") -> 7 | H2: =COUNTIFS('Issue Register'!$B:$B,$A2,'Issue Register'!$D:$D,"Rejected") -> 0 | I2: =COUNTIFS('Issue Register'!$B:$B,$A2,'Issue Register'!$D:$D,"Confirmed") -> 7 | J2: =MAX(0,100-(C2*15+D2*8+E2*3+F2*1)) -> 62
A3: A2 | B3: apps/web/src/lib core (roles, actions, notifications, assistant) | C3: =COUNTIFS('Issue Register'!$B:$B,$A3,'Issue Register'!$L:$L,"S1",'Issue Register'!$D:$D,"<>Rejected") -> 0 | D3: =COUNTIFS('Issue Register'!$B:$B,$A3,'Issue Register'!$L:$L,"S2",'Issue Register'!$D:$D,"<>Rejected") -> 1 | E3: =COUNTIFS('Issue Register'!$B:$B,$A3,'Issue Register'!$L:$L,"S3",'Issue Register'!$D:$D,"<>Rejected") -> 8 | F3: =COUNTIFS('Issue Register'!$B:$B,$A3,'Issue Register'!$L:$L,"S4",'Issue Register'!$D:$D,"<>Rejected") -> 3 | G3: =COUNTIFS('Issue Register'!$B:$B,$A3,'Issue Register'!$D:$D,"Confirmed") -> 12 | H3: =COUNTIFS('Issue Register'!$B:$B,$A3,'Issue Register'!$D:$D,"Rejected") -> 0 | I3: =COUNTIFS('Issue Register'!$B:$B,$A3,'Issue Register'!$D:$D,"Confirmed") -> 12 | J3: =MAX(0,100-(C3*15+D3*8+E3*3+F3*1)) -> 65
A4: A3 | B4: apps/web/src/lib/services | C4: =COUNTIFS('Issue Register'!$B:$B,$A4,'Issue Register'!$L:$L,"S1",'Issue Register'!$D:$D,"<>Rejected") -> 0 | D4: =COUNTIFS('Issue Register'!$B:$B,$A4,'Issue Register'!$L:$L,"S2",'Issue Register'!$D:$D,"<>Rejected") -> 2 | E4: =COUNTIFS('Issue Register'!$B:$B,$A4,'Issue Register'!$L:$L,"S3",'Issue Register'!$D:$D,"<>Rejected") -> 5 | F4: =COUNTIFS('Issue Register'!$B:$B,$A4,'Issue Register'!$L:$L,"S4",'Issue Register'!$D:$D,"<>Rejected") -> 0 | G4: =COUNTIFS('Issue Register'!$B:$B,$A4,'Issue Register'!$D:$D,"Confirmed") -> 7 | H4: =COUNTIFS('Issue Register'!$B:$B,$A4,'Issue Register'!$D:$D,"Rejected") -> 0 | I4: =COUNTIFS('Issue Register'!$B:$B,$A4,'Issue Register'!$D:$D,"Confirmed") -> 7 | J4: =MAX(0,100-(C4*15+D4*8+E4*3+F4*1)) -> 69
A5: A4 | B5: apps/web/src/lib/api | C5: =COUNTIFS('Issue Register'!$B:$B,$A5,'Issue Register'!$L:$L,"S1",'Issue Register'!$D:$D,"<>Rejected") -> 0 | D5: =COUNTIFS('Issue Register'!$B:$B,$A5,'Issue Register'!$L:$L,"S2",'Issue Register'!$D:$D,"<>Rejected") -> 1 | E5: =COUNTIFS('Issue Register'!$B:$B,$A5,'Issue Register'!$L:$L,"S3",'Issue Register'!$D:$D,"<>Rejected") -> 3 | F5: =COUNTIFS('Issue Register'!$B:$B,$A5,'Issue Register'!$L:$L,"S4",'Issue Register'!$D:$D,"<>Rejected") -> 2 | G5: =COUNTIFS('Issue Register'!$B:$B,$A5,'Issue Register'!$D:$D,"Confirmed") -> 6 | H5: =COUNTIFS('Issue Register'!$B:$B,$A5,'Issue Register'!$D:$D,"Rejected") -> 0 | I5: =COUNTIFS('Issue Register'!$B:$B,$A5,'Issue Register'!$D:$D,"Confirmed") -> 6 | J5: =MAX(0,100-(C5*15+D5*8+E5*3+F5*1)) -> 81
A6: A5 | B6: apps/web/src/app/api (v1, oauth, external) | C6: =COUNTIFS('Issue Register'!$B:$B,$A6,'Issue Register'!$L:$L,"S1",'Issue Register'!$D:$D,"<>Rejected") -> 0 | D6: =COUNTIFS('Issue Register'!$B:$B,$A6,'Issue Register'!$L:$L,"S2",'Issue Register'!$D:$D,"<>Rejected") -> 0 | E6: =COUNTIFS('Issue Register'!$B:$B,$A6,'Issue Register'!$L:$L,"S3",'Issue Register'!$D:$D,"<>Rejected") -> 5 | F6: =COUNTIFS('Issue Register'!$B:$B,$A6,'Issue Register'!$L:$L,"S4",'Issue Register'!$D:$D,"<>Rejected") -> 3 | G6: =COUNTIFS('Issue Register'!$B:$B,$A6,'Issue Register'!$D:$D,"Confirmed") -> 8 | H6: =COUNTIFS('Issue Register'!$B:$B,$A6,'Issue Register'!$D:$D,"Rejected") -> 1 | I6: =COUNTIFS('Issue Register'!$B:$B,$A6,'Issue Register'!$D:$D,"Confirmed") -> 8 | J6: =MAX(0,100-(C6*15+D6*8+E6*3+F6*1)) -> 82
A7: A6 | B7: app/(app): projects, jobs, schedule, files, selections, tasks | C7: =COUNTIFS('Issue Register'!$B:$B,$A7,'Issue Register'!$L:$L,"S1",'Issue Register'!$D:$D,"<>Rejected") -> 1 | D7: =COUNTIFS('Issue Register'!$B:$B,$A7,'Issue Register'!$L:$L,"S2",'Issue Register'!$D:$D,"<>Rejected") -> 1 | E7: =COUNTIFS('Issue Register'!$B:$B,$A7,'Issue Register'!$L:$L,"S3",'Issue Register'!$D:$D,"<>Rejected") -> 1 | F7: =COUNTIFS('Issue Register'!$B:$B,$A7,'Issue Register'!$L:$L,"S4",'Issue Register'!$D:$D,"<>Rejected") -> 1 | G7: =COUNTIFS('Issue Register'!$B:$B,$A7,'Issue Register'!$D:$D,"Confirmed") -> 4 | H7: =COUNTIFS('Issue Register'!$B:$B,$A7,'Issue Register'!$D:$D,"Rejected") -> 0 | I7: =COUNTIFS('Issue Register'!$B:$B,$A7,'Issue Register'!$D:$D,"Confirmed") -> 4 | J7: =MAX(0,100-(C7*15+D7*8+E7*3+F7*1)) -> 73
A8: A7 | B8: app/(app): crm, clients, estimates, financials, inbox, vendors, contracts, dashboard | C8: =COUNTIFS('Issue Register'!$B:$B,$A8,'Issue Register'!$L:$L,"S1",'Issue Register'!$D:$D,"<>Rejected") -> 2 | D8: =COUNTIFS('Issue Register'!$B:$B,$A8,'Issue Register'!$L:$L,"S2",'Issue Register'!$D:$D,"<>Rejected") -> 1 | E8: =COUNTIFS('Issue Register'!$B:$B,$A8,'Issue Register'!$L:$L,"S3",'Issue Register'!$D:$D,"<>Rejected") -> 2 | F8: =COUNTIFS('Issue Register'!$B:$B,$A8,'Issue Register'!$L:$L,"S4",'Issue Register'!$D:$D,"<>Rejected") -> 0 | G8: =COUNTIFS('Issue Register'!$B:$B,$A8,'Issue Register'!$D:$D,"Confirmed") -> 5 | H8: =COUNTIFS('Issue Register'!$B:$B,$A8,'Issue Register'!$D:$D,"Rejected") -> 1 | I8: =COUNTIFS('Issue Register'!$B:$B,$A8,'Issue Register'!$D:$D,"Confirmed") -> 5 | J8: =MAX(0,100-(C8*15+D8*8+E8*3+F8*1)) -> 56
A9: A8 | B9: app/(app)/settings + auth.ts / auth.config.ts / middleware.ts + login/invite/reset routes | C9: =COUNTIFS('Issue Register'!$B:$B,$A9,'Issue Register'!$L:$L,"S1",'Issue Register'!$D:$D,"<>Rejected") -> 2 | D9: =COUNTIFS('Issue Register'!$B:$B,$A9,'Issue Register'!$L:$L,"S2",'Issue Register'!$D:$D,"<>Rejected") -> 2 | E9: =COUNTIFS('Issue Register'!$B:$B,$A9,'Issue Register'!$L:$L,"S3",'Issue Register'!$D:$D,"<>Rejected") -> 2 | F9: =COUNTIFS('Issue Register'!$B:$B,$A9,'Issue Register'!$L:$L,"S4",'Issue Register'!$D:$D,"<>Rejected") -> 2 | G9: =COUNTIFS('Issue Register'!$B:$B,$A9,'Issue Register'!$D:$D,"Confirmed") -> 8 | H9: =COUNTIFS('Issue Register'!$B:$B,$A9,'Issue Register'!$D:$D,"Rejected") -> 0 | I9: =COUNTIFS('Issue Register'!$B:$B,$A9,'Issue Register'!$D:$D,"Confirmed") -> 8 | J9: =MAX(0,100-(C9*15+D9*8+E9*3+F9*1)) -> 46
A10: A9 | B10: components + globals.css + layout + tailwind config | C10: =COUNTIFS('Issue Register'!$B:$B,$A10,'Issue Register'!$L:$L,"S1",'Issue Register'!$D:$D,"<>Rejected") -> 0 | D10: =COUNTIFS('Issue Register'!$B:$B,$A10,'Issue Register'!$L:$L,"S2",'Issue Register'!$D:$D,"<>Rejected") -> 0 | E10: =COUNTIFS('Issue Register'!$B:$B,$A10,'Issue Register'!$L:$L,"S3",'Issue Register'!$D:$D,"<>Rejected") -> 2 | F10: =COUNTIFS('Issue Register'!$B:$B,$A10,'Issue Register'!$L:$L,"S4",'Issue Register'!$D:$D,"<>Rejected") -> 9 | G10: =COUNTIFS('Issue Register'!$B:$B,$A10,'Issue Register'!$D:$D,"Confirmed") -> 11 | H10: =COUNTIFS('Issue Register'!$B:$B,$A10,'Issue Register'!$D:$D,"Rejected") -> 1 | I10: =COUNTIFS('Issue Register'!$B:$B,$A10,'Issue Register'!$D:$D,"Confirmed") -> 11 | J10: =MAX(0,100-(C10*15+D10*8+E10*3+F10*1)) -> 85
A11: A10 | B11: lib integration clients (quickbooks, jobtread, quo, m365, sharepoint, oauth) + app integrations pages | C11: =COUNTIFS('Issue Register'!$B:$B,$A11,'Issue Register'!$L:$L,"S1",'Issue Register'!$D:$D,"<>Rejected") -> 3 | D11: =COUNTIFS('Issue Register'!$B:$B,$A11,'Issue Register'!$L:$L,"S2",'Issue Register'!$D:$D,"<>Rejected") -> 3 | E11: =COUNTIFS('Issue Register'!$B:$B,$A11,'Issue Register'!$L:$L,"S3",'Issue Register'!$D:$D,"<>Rejected") -> 8 | F11: =COUNTIFS('Issue Register'!$B:$B,$A11,'Issue Register'!$L:$L,"S4",'Issue Register'!$D:$D,"<>Rejected") -> 1 | G11: =COUNTIFS('Issue Register'!$B:$B,$A11,'Issue Register'!$D:$D,"Confirmed") -> 15 | H11: =COUNTIFS('Issue Register'!$B:$B,$A11,'Issue Register'!$D:$D,"Rejected") -> 0 | I11: =COUNTIFS('Issue Register'!$B:$B,$A11,'Issue Register'!$D:$D,"Confirmed") -> 15 | J11: =MAX(0,100-(C11*15+D11*8+E11*3+F11*1)) -> 6
A12: A11 | B12: Root config, .github, deploy, docs, ecosystem.config.js, imports | C12: =COUNTIFS('Issue Register'!$B:$B,$A12,'Issue Register'!$L:$L,"S1",'Issue Register'!$D:$D,"<>Rejected") -> 1 | D12: =COUNTIFS('Issue Register'!$B:$B,$A12,'Issue Register'!$L:$L,"S2",'Issue Register'!$D:$D,"<>Rejected") -> 4 | E12: =COUNTIFS('Issue Register'!$B:$B,$A12,'Issue Register'!$L:$L,"S3",'Issue Register'!$D:$D,"<>Rejected") -> 2 | F12: =COUNTIFS('Issue Register'!$B:$B,$A12,'Issue Register'!$L:$L,"S4",'Issue Register'!$D:$D,"<>Rejected") -> 3 | G12: =COUNTIFS('Issue Register'!$B:$B,$A12,'Issue Register'!$D:$D,"Confirmed") -> 10 | H12: =COUNTIFS('Issue Register'!$B:$B,$A12,'Issue Register'!$D:$D,"Rejected") -> 0 | I12: =COUNTIFS('Issue Register'!$B:$B,$A12,'Issue Register'!$D:$D,"Confirmed") -> 10 | J12: =MAX(0,100-(C12*15+D12*8+E12*3+F12*1)) -> 44
A13: A0 | B13: cross-cutting (no single folder owns) | C13: =COUNTIFS('Issue Register'!$B:$B,$A13,'Issue Register'!$L:$L,"S1",'Issue Register'!$D:$D,"<>Rejected") -> 1 | D13: =COUNTIFS('Issue Register'!$B:$B,$A13,'Issue Register'!$L:$L,"S2",'Issue Register'!$D:$D,"<>Rejected") -> 2 | E13: =COUNTIFS('Issue Register'!$B:$B,$A13,'Issue Register'!$L:$L,"S3",'Issue Register'!$D:$D,"<>Rejected") -> 0 | F13: =COUNTIFS('Issue Register'!$B:$B,$A13,'Issue Register'!$L:$L,"S4",'Issue Register'!$D:$D,"<>Rejected") -> 1 | G13: =COUNTIFS('Issue Register'!$B:$B,$A13,'Issue Register'!$D:$D,"Confirmed") -> 4 | H13: =COUNTIFS('Issue Register'!$B:$B,$A13,'Issue Register'!$D:$D,"Rejected") -> 0 | I13: =COUNTIFS('Issue Register'!$B:$B,$A13,'Issue Register'!$D:$D,"Confirmed") -> 4 | J13: =MAX(0,100-(C13*15+D13*8+E13*3+F13*1)) -> 68
B14: Health score = 100 − (15·S1 + 8·S2 + 3·S3 + 1·S4), floor 0. Rejected rows excluded from counts.

Sheet Summary
A1: HENLEY HUB AUDIT — SUMMARY
A3: Total rows filed | B3: =COUNTA('Issue Register'!$A$2:$A$141) -> 100
A4: Confirmed | B4: =COUNTIF('Issue Register'!$D:$D,"Confirmed") -> 97
A5: Rejected | B5: =COUNTIF('Issue Register'!$D:$D,"Rejected") -> 3
A6: Still on Verify | B6: =COUNTIF('Issue Register'!$D:$D,"Verify") -> 0 | C6: Must be 0 at audit acceptance.
A7: Fixed | B7: =COUNTIF('Issue Register'!$D:$D,"Fixed") -> 0
A9: By severity (excl. Rejected)
A10: S1 | B10: =COUNTIFS('Issue Register'!$L:$L,"S1",'Issue Register'!$D:$D,"<>Rejected") -> 11
A11: S2 | B11: =COUNTIFS('Issue Register'!$L:$L,"S2",'Issue Register'!$D:$D,"<>Rejected") -> 18
A12: S3 | B12: =COUNTIFS('Issue Register'!$L:$L,"S3",'Issue Register'!$D:$D,"<>Rejected") -> 43
A13: S4 | B13: =COUNTIFS('Issue Register'!$L:$L,"S4",'Issue Register'!$D:$D,"<>Rejected") -> 25
A15: READINESS CHECKS
A16: Critical (S1) still unfixed | B16: =COUNTIFS('Issue Register'!$L:$L,"S1",'Issue Register'!$D:$D,"Confirmed") -> 11 | C16: S1 rows Confirmed but not yet Fixed.
A17: Rows with no file path yet | B17: =SUMPRODUCT(('Issue Register'!$A$2:$A$141<>"")*('Issue Register'!$F$2:$F$141="")) -> 0 | C17: MUST be 0 before this register is accepted.
A18: Fixed rows missing a commit hash | B18: =SUMPRODUCT(('Issue Register'!$D$2:$D$141="Fixed")*('Issue Register'!$T$2:$T$141="")) -> 0 | C18: Fix phase gate: every Fixed row needs a hash.
